mcp_hydrolix/__init__.py
mcp_hydrolix/main.py
mcp_hydrolix/mcp_env.py
mcp_hydrolix/mcp_server.py
iflow_mcp_mcp_hydrolix-0.1.5.dist-info/METADATA
iflow_mcp_mcp_hydrolix-0.1.5.dist-info/WHEEL
iflow_mcp_mcp_hydrolix-0.1.5.dist-info/entry_points.txt
iflow_mcp_mcp_hydrolix-0.1.5.dist-info/licenses/LICENSE
iflow_mcp_mcp_hydrolix-0.1.5.dist-info/RECORD
