Metadata-Version: 2.4
Name: iflow-mcp_mcp-hydrolix
Version: 0.1.5
Summary: An MCP server for Hydrolix.
Project-URL: Home, https://github.com/hydrolix/mcp-hydrolix
License-Expression: Apache-2.0
License-File: LICENSE
Requires-Python: >=3.13
Requires-Dist: clickhouse-connect>=0.8.16
Requires-Dist: fastmcp>=2.0.0
Requires-Dist: pip-system-certs>=4.0
Requires-Dist: python-dotenv>=1.0.1
Provides-Extra: dev
Requires-Dist: pre-commit; extra == 'dev'
Requires-Dist: pytest; extra == 'dev'
Requires-Dist: pytest-asyncio; extra == 'dev'
Requires-Dist: ruff; extra == 'dev'
